pyjsmath-0.2.1.dist-info/METADATA
pyjsmath-0.2.1.dist-info/WHEEL
pyjsmath/__init__.py
pyjsmath/__init__.pyi
pyjsmath/py.typed
pyjsmath/pyjsmath.cp313-win_amd64.pyd
pyjsmath-0.2.1.dist-info/RECORD
