Metadata-Version: 2.3
Name: pyjsmath
Version: 0.2.1
Classifier: Programming Language :: Rust
Classifier: Programming Language :: Python :: Implementation :: CPython
Classifier: Programming Language :: Python :: Implementation :: PyPy
Summary: Fast math for python written in rust.
Author: anamoyee
License: GPL-3.0
Requires-Python: >=3.8
Project-URL: Source Code, https://github.com/anamoyee/pyjsmath
